<?xml version="1.0" encoding="utf-8"?><index><!-- saved from url=(0016)http://localhost -->
<stem n="vigation"><phr n="Navigation"><ent r="64" t="4" w="73" /><ent r="64" t="4" w="73" /><ent r="92" t="4" w="81" /><ent r="92" t="4" w="81" /></phr><phr n="navigation"><ent r="3" t="4" w="95" /><ent r="3" t="4" w="95" /></phr><phr n="navigational"><ent r="69" t="15" w="1634" /><ent r="69" t="15" w="1634" /></phr></stem><stem n="navigatio"><phr n="Navigation"><ent r="64" t="4" w="73" /><ent r="64" t="4" w="73" /><ent r="92" t="4" w="81" /><ent r="92" t="4" w="81" /></phr><phr n="navigation"><ent r="3" t="4" w="95" /><ent r="3" t="4" w="95" /></phr><phr n="navigational"><ent r="69" t="15" w="1634" /><ent r="69" t="15" w="1634" /></phr></stem><stem n="avigation"><phr n="Navigation"><ent r="64" t="4" w="73" /><ent r="64" t="4" w="73" /><ent r="92" t="4" w="81" /><ent r="92" t="4" w="81" /></phr><phr n="navigation"><ent r="3" t="4" w="95" /><ent r="3" t="4" w="95" /></phr><phr n="navigational"><ent r="69" t="15" w="1634" /><ent r="69" t="15" w="1634" /></phr></stem><stem n="navigation"><phr n="Navigation"><ent r="64" t="4" w="73" /><ent r="64" t="4" w="73" /><ent r="92" t="4" w="81" /><ent r="92" t="4" w="81" /></phr><phr n="navigation"><ent r="3" t="4" w="95" /><ent r="3" t="4" w="95" /></phr><phr n="navigational"><ent r="69" t="15" w="1634" /><ent r="69" t="15" w="1634" /></phr></stem><stem n="toolbar"><phr n="Toolbar"><ent r="64" t="4" w="74" /><ent r="64" t="4" w="74" /><ent r="92" t="4" w="82" /><ent r="92" t="4" w="82" /></phr><phr n="toolbar"><ent r="3" t="4" w="96" /><ent r="3" t="4" w="96" /><ent r="3" t="4" w="104" /><ent r="3" t="4" w="104" /><ent r="3" t="4" w="129" /><ent r="3" t="4" w="438" /><ent r="3" t="39" w="277" /><ent r="3" t="40" w="324" /><ent r="3" t="42" w="636" /><ent r="3" t="43" w="634" /><ent r="3" t="44" w="724" /><ent r="3" t="45" w="404" /><ent r="3" t="46" w="353" /><ent r="3" t="61" w="174" /><ent r="3" t="62" w="163" /><ent r="3" t="63" w="166" /><ent r="3" t="64" w="217" /><ent r="3" t="65" w="331" /><ent r="3" t="66" w="188" /><ent r="3" t="67" w="173" /><ent r="3" t="68" w="168" /><ent r="3" t="69" w="164" /><ent r="3" t="70" w="269" /><ent r="3" t="71" w="221" /><ent r="3" t="72" w="250" /><ent r="3" t="73" w="228" /><ent r="3" t="74" w="209" /><ent r="3" t="75" w="188" /><ent r="3" t="76" w="303" /></phr></stem><stem n="lba"><phr n="Toolbar"><ent r="64" t="4" w="74" /><ent r="64" t="4" w="74" /><ent r="92" t="4" w="82" /><ent r="92" t="4" w="82" /></phr><phr n="toolbar"><ent r="3" t="4" w="96" /><ent r="3" t="4" w="96" /><ent r="3" t="4" w="104" /><ent r="3" t="4" w="104" /><ent r="3" t="4" w="129" /><ent r="3" t="4" w="438" /><ent r="3" t="39" w="277" /><ent r="3" t="40" w="324" /><ent r="3" t="42" w="636" /><ent r="3" t="43" w="634" /><ent r="3" t="44" w="724" /><ent r="3" t="45" w="404" /><ent r="3" t="46" w="353" /><ent r="3" t="61" w="174" /><ent r="3" t="62" w="163" /><ent r="3" t="63" w="166" /><ent r="3" t="64" w="217" /><ent r="3" t="65" w="331" /><ent r="3" t="66" w="188" /><ent r="3" t="67" w="173" /><ent r="3" t="68" w="168" /><ent r="3" t="69" w="164" /><ent r="3" t="70" w="269" /><ent r="3" t="71" w="221" /><ent r="3" t="72" w="250" /><ent r="3" t="73" w="228" /><ent r="3" t="74" w="209" /><ent r="3" t="75" w="188" /><ent r="3" t="76" w="303" /></phr></stem><stem n="bar"><phr n="Toolbar"><ent r="64" t="4" w="74" /><ent r="64" t="4" w="74" /><ent r="92" t="4" w="82" /><ent r="92" t="4" w="82" /></phr><phr n="Sidebar"><ent r="64" t="4" w="76" /><ent r="64" t="4" w="76" /><ent r="92" t="4" w="206" /><ent r="92" t="4" w="206" /></phr><phr n="toolbar"><ent r="3" t="4" w="96" /><ent r="3" t="4" w="96" /><ent r="3" t="4" w="104" /><ent r="3" t="4" w="104" /><ent r="3" t="4" w="129" /><ent r="3" t="4" w="438" /><ent r="3" t="39" w="277" /><ent r="3" t="40" w="324" /><ent r="3" t="42" w="636" /><ent r="3" t="43" w="634" /><ent r="3" t="44" w="724" /><ent r="3" t="45" w="404" /><ent r="3" t="46" w="353" /><ent r="3" t="61" w="174" /><ent r="3" t="62" w="163" /><ent r="3" t="63" w="166" /><ent r="3" t="64" w="217" /><ent r="3" t="65" w="331" /><ent r="3" t="66" w="188" /><ent r="3" t="67" w="173" /><ent r="3" t="68" w="168" /><ent r="3" t="69" w="164" /><ent r="3" t="70" w="269" /><ent r="3" t="71" w="221" /><ent r="3" t="72" w="250" /><ent r="3" t="73" w="228" /><ent r="3" t="74" w="209" /><ent r="3" t="75" w="188" /><ent r="3" t="76" w="303" /></phr><phr n="sidebar"><ent r="3" t="4" w="219" /><ent r="3" t="4" w="219" /><ent r="3" t="4" w="228" /><ent r="3" t="4" w="228" /><ent r="3" t="4" w="244" /><ent r="3" t="4" w="244" /><ent r="3" t="4" w="287" /><ent r="3" t="4" w="287" /><ent r="3" t="4" w="302" /><ent r="3" t="4" w="306" /><ent r="3" t="4" w="306" /><ent r="3" t="7" w="300" /><ent r="3" t="7" w="406" /><ent r="3" t="9" w="68" /><ent r="3" t="11" w="168" /><ent r="3" t="12" w="336" /><ent r="3" t="13" w="78" /><ent r="3" t="16" w="310" /><ent r="3" t="17" w="343" /><ent r="3" t="17" w="485" /><ent r="3" t="17" w="678" /><ent r="3" t="18" w="347" /><ent r="3" t="19" w="330" /><ent r="3" t="20" w="331" /><ent r="3" t="21" w="245" /><ent r="3" t="22" w="334" /><ent r="3" t="23" w="602" /><ent r="3" t="25" w="652" /><ent r="3" t="27" w="488" /><ent r="3" t="29" w="211" /><ent r="3" t="30" w="197" /><ent r="3" t="31" w="192" /><ent r="3" t="32" w="365" /><ent r="3" t="34" w="239" /><ent r="3" t="49" w="81" /><ent r="3" t="50" w="508" /><ent r="3" t="52" w="208" /><ent r="3" t="52" w="308" /><ent r="3" t="52" w="905" /><ent r="3" t="52" w="1020" /><ent r="3" t="53" w="193" /><ent r="3" t="54" w="266" /><ent r="3" t="55" w="278" /><ent r="3" t="56" w="242" /><ent r="3" t="57" w="266" /><ent r="3" t="58" w="116" /></phr><phr n="bar"><ent r="3" t="4" w="350" /><ent r="3" t="4" w="350" /><ent r="3" t="4" w="360" /><ent r="3" t="4" w="360" /><ent r="3" t="4" w="395" /><ent r="3" t="4" w="395" /></phr><phr n="Bar"><ent r="82" t="4" w="356" /><ent r="82" t="4" w="356" /></phr><phr n="WEBARCHIVE"><ent r="3" t="50" w="253" /></phr></stem><stem n="olb"><phr n="Toolbar"><ent r="64" t="4" w="74" /><ent r="64" t="4" w="74" /><ent r="92" t="4" w="82" /><ent r="92" t="4" w="82" /></phr><phr n="toolbar"><ent r="3" t="4" w="96" /><ent r="3" t="4" w="96" /><ent r="3" t="4" w="104" /><ent r="3" t="4" w="104" /><ent r="3" t="4" w="129" /><ent r="3" t="4" w="438" /><ent r="3" t="39" w="277" /><ent r="3" t="40" w="324" /><ent r="3" t="42" w="636" /><ent r="3" t="43" w="634" /><ent r="3" t="44" w="724" /><ent r="3" t="45" w="404" /><ent r="3" t="46" w="353" /><ent r="3" t="61" w="174" /><ent r="3" t="62" w="163" /><ent r="3" t="63" w="166" /><ent r="3" t="64" w="217" /><ent r="3" t="65" w="331" /><ent r="3" t="66" w="188" /><ent r="3" t="67" w="173" /><ent r="3" t="68" w="168" /><ent r="3" t="69" w="164" /><ent r="3" t="70" w="269" /><ent r="3" t="71" w="221" /><ent r="3" t="72" w="250" /><ent r="3" t="73" w="228" /><ent r="3" t="74" w="209" /><ent r="3" t="75" w="188" /><ent r="3" t="76" w="303" /></phr></stem><stem n="oolb"><phr n="Toolbar"><ent r="64" t="4" w="74" /><ent r="64" t="4" w="74" /><ent r="92" t="4" w="82" /><ent r="92" t="4" w="82" /></phr><phr n="toolbar"><ent r="3" t="4" w="96" /><ent r="3" t="4" w="96" /><ent r="3" t="4" w="104" /><ent r="3" t="4" w="104" /><ent r="3" t="4" w="129" /><ent r="3" t="4" w="438" /><ent r="3" t="39" w="277" /><ent r="3" t="40" w="324" /><ent r="3" t="42" w="636" /><ent r="3" t="43" w="634" /><ent r="3" t="44" w="724" /><ent r="3" t="45" w="404" /><ent r="3" t="46" w="353" /><ent r="3" t="61" w="174" /><ent r="3" t="62" w="163" /><ent r="3" t="63" w="166" /><ent r="3" t="64" w="217" /><ent r="3" t="65" w="331" /><ent r="3" t="66" w="188" /><ent r="3" t="67" w="173" /><ent r="3" t="68" w="168" /><ent r="3" t="69" w="164" /><ent r="3" t="70" w="269" /><ent r="3" t="71" w="221" /><ent r="3" t="72" w="250" /><ent r="3" t="73" w="228" /><ent r="3" t="74" w="209" /><ent r="3" t="75" w="188" /><ent r="3" t="76" w="303" /></phr></stem><stem n="olba"><phr n="Toolbar"><ent r="64" t="4" w="74" /><ent r="64" t="4" w="74" /><ent r="92" t="4" w="82" /><ent r="92" t="4" w="82" /></phr><phr n="toolbar"><ent r="3" t="4" w="96" /><ent r="3" t="4" w="96" /><ent r="3" t="4" w="104" /><ent r="3" t="4" w="104" /><ent r="3" t="4" w="129" /><ent r="3" t="4" w="438" /><ent r="3" t="39" w="277" /><ent r="3" t="40" w="324" /><ent r="3" t="42" w="636" /><ent r="3" t="43" w="634" /><ent r="3" t="44" w="724" /><ent r="3" t="45" w="404" /><ent r="3" t="46" w="353" /><ent r="3" t="61" w="174" /><ent r="3" t="62" w="163" /><ent r="3" t="63" w="166" /><ent r="3" t="64" w="217" /><ent r="3" t="65" w="331" /><ent r="3" t="66" w="188" /><ent r="3" t="67" w="173" /><ent r="3" t="68" w="168" /><ent r="3" t="69" w="164" /><ent r="3" t="70" w="269" /><ent r="3" t="71" w="221" /><ent r="3" t="72" w="250" /><ent r="3" t="73" w="228" /><ent r="3" t="74" w="209" /><ent r="3" t="75" w="188" /><ent r="3" t="76" w="303" /></phr></stem><stem n="lbar"><phr n="Toolbar"><ent r="64" t="4" w="74" /><ent r="64" t="4" w="74" /><ent r="92" t="4" w="82" /><ent r="92" t="4" w="82" /></phr><phr n="toolbar"><ent r="3" t="4" w="96" /><ent r="3" t="4" w="96" /><ent r="3" t="4" w="104" /><ent r="3" t="4" w="104" /><ent r="3" t="4" w="129" /><ent r="3" t="4" w="438" /><ent r="3" t="39" w="277" /><ent r="3" t="40" w="324" /><ent r="3" t="42" w="636" /><ent r="3" t="43" w="634" /><ent r="3" t="44" w="724" /><ent r="3" t="45" w="404" /><ent r="3" t="46" w="353" /><ent r="3" t="61" w="174" /><ent r="3" t="62" w="163" /><ent r="3" t="63" w="166" /><ent r="3" t="64" w="217" /><ent r="3" t="65" w="331" /><ent r="3" t="66" w="188" /><ent r="3" t="67" w="173" /><ent r="3" t="68" w="168" /><ent r="3" t="69" w="164" /><ent r="3" t="70" w="269" /><ent r="3" t="71" w="221" /><ent r="3" t="72" w="250" /><ent r="3" t="73" w="228" /><ent r="3" t="74" w="209" /><ent r="3" t="75" w="188" /><ent r="3" t="76" w="303" /></phr></stem><stem n="toolb"><phr n="Toolbar"><ent r="64" t="4" w="74" /><ent r="64" t="4" w="74" /><ent r="92" t="4" w="82" /><ent r="92" t="4" w="82" /></phr><phr n="toolbar"><ent r="3" t="4" w="96" /><ent r="3" t="4" w="96" /><ent r="3" t="4" w="104" /><ent r="3" t="4" w="104" /><ent r="3" t="4" w="129" /><ent r="3" t="4" w="438" /><ent r="3" t="39" w="277" /><ent r="3" t="40" w="324" /><ent r="3" t="42" w="636" /><ent r="3" t="43" w="634" /><ent r="3" t="44" w="724" /><ent r="3" t="45" w="404" /><ent r="3" t="46" w="353" /><ent r="3" t="61" w="174" /><ent r="3" t="62" w="163" /><ent r="3" t="63" w="166" /><ent r="3" t="64" w="217" /><ent r="3" t="65" w="331" /><ent r="3" t="66" w="188" /><ent r="3" t="67" w="173" /><ent r="3" t="68" w="168" /><ent r="3" t="69" w="164" /><ent r="3" t="70" w="269" /><ent r="3" t="71" w="221" /><ent r="3" t="72" w="250" /><ent r="3" t="73" w="228" /><ent r="3" t="74" w="209" /><ent r="3" t="75" w="188" /><ent r="3" t="76" w="303" /></phr></stem><stem n="oolba"><phr n="Toolbar"><ent r="64" t="4" w="74" /><ent r="64" t="4" w="74" /><ent r="92" t="4" w="82" /><ent r="92" t="4" w="82" /></phr><phr n="toolbar"><ent r="3" t="4" w="96" /><ent r="3" t="4" w="96" /><ent r="3" t="4" w="104" /><ent r="3" t="4" w="104" /><ent r="3" t="4" w="129" /><ent r="3" t="4" w="438" /><ent r="3" t="39" w="277" /><ent r="3" t="40" w="324" /><ent r="3" t="42" w="636" /><ent r="3" t="43" w="634" /><ent r="3" t="44" w="724" /><ent r="3" t="45" w="404" /><ent r="3" t="46" w="353" /><ent r="3" t="61" w="174" /><ent r="3" t="62" w="163" /><ent r="3" t="63" w="166" /><ent r="3" t="64" w="217" /><ent r="3" t="65" w="331" /><ent r="3" t="66" w="188" /><ent r="3" t="67" w="173" /><ent r="3" t="68" w="168" /><ent r="3" t="69" w="164" /><ent r="3" t="70" w="269" /><ent r="3" t="71" w="221" /><ent r="3" t="72" w="250" /><ent r="3" t="73" w="228" /><ent r="3" t="74" w="209" /><ent r="3" t="75" w="188" /><ent r="3" t="76" w="303" /></phr></stem><stem n="olbar"><phr n="Toolbar"><ent r="64" t="4" w="74" /><ent r="64" t="4" w="74" /><ent r="92" t="4" w="82" /><ent r="92" t="4" w="82" /></phr><phr n="toolbar"><ent r="3" t="4" w="96" /><ent r="3" t="4" w="96" /><ent r="3" t="4" w="104" /><ent r="3" t="4" w="104" /><ent r="3" t="4" w="129" /><ent r="3" t="4" w="438" /><ent r="3" t="39" w="277" /><ent r="3" t="40" w="324" /><ent r="3" t="42" w="636" /><ent r="3" t="43" w="634" /><ent r="3" t="44" w="724" /><ent r="3" t="45" w="404" /><ent r="3" t="46" w="353" /><ent r="3" t="61" w="174" /><ent r="3" t="62" w="163" /><ent r="3" t="63" w="166" /><ent r="3" t="64" w="217" /><ent r="3" t="65" w="331" /><ent r="3" t="66" w="188" /><ent r="3" t="67" w="173" /><ent r="3" t="68" w="168" /><ent r="3" t="69" w="164" /><ent r="3" t="70" w="269" /><ent r="3" t="71" w="221" /><ent r="3" t="72" w="250" /><ent r="3" t="73" w="228" /><ent r="3" t="74" w="209" /><ent r="3" t="75" w="188" /><ent r="3" t="76" w="303" /></phr></stem><stem n="toolba"><phr n="Toolbar"><ent r="64" t="4" w="74" /><ent r="64" t="4" w="74" /><ent r="92" t="4" w="82" /><ent r="92" t="4" w="82" /></phr><phr n="toolbar"><ent r="3" t="4" w="96" /><ent r="3" t="4" w="96" /><ent r="3" t="4" w="104" /><ent r="3" t="4" w="104" /><ent r="3" t="4" w="129" /><ent r="3" t="4" w="438" /><ent r="3" t="39" w="277" /><ent r="3" t="40" w="324" /><ent r="3" t="42" w="636" /><ent r="3" t="43" w="634" /><ent r="3" t="44" w="724" /><ent r="3" t="45" w="404" /><ent r="3" t="46" w="353" /><ent r="3" t="61" w="174" /><ent r="3" t="62" w="163" /><ent r="3" t="63" w="166" /><ent r="3" t="64" w="217" /><ent r="3" t="65" w="331" /><ent r="3" t="66" w="188" /><ent r="3" t="67" w="173" /><ent r="3" t="68" w="168" /><ent r="3" t="69" w="164" /><ent r="3" t="70" w="269" /><ent r="3" t="71" w="221" /><ent r="3" t="72" w="250" /><ent r="3" t="73" w="228" /><ent r="3" t="74" w="209" /><ent r="3" t="75" w="188" /><ent r="3" t="76" w="303" /></phr></stem><stem n="oolbar"><phr n="Toolbar"><ent r="64" t="4" w="74" /><ent r="64" t="4" w="74" /><ent r="92" t="4" w="82" /><ent r="92" t="4" w="82" /></phr><phr n="toolbar"><ent r="3" t="4" w="96" /><ent r="3" t="4" w="96" /><ent r="3" t="4" w="104" /><ent r="3" t="4" w="104" /><ent r="3" t="4" w="129" /><ent r="3" t="4" w="438" /><ent r="3" t="39" w="277" /><ent r="3" t="40" w="324" /><ent r="3" t="42" w="636" /><ent r="3" t="43" w="634" /><ent r="3" t="44" w="724" /><ent r="3" t="45" w="404" /><ent r="3" t="46" w="353" /><ent r="3" t="61" w="174" /><ent r="3" t="62" w="163" /><ent r="3" t="63" w="166" /><ent r="3" t="64" w="217" /><ent r="3" t="65" w="331" /><ent r="3" t="66" w="188" /><ent r="3" t="67" w="173" /><ent r="3" t="68" w="168" /><ent r="3" t="69" w="164" /><ent r="3" t="70" w="269" /><ent r="3" t="71" w="221" /><ent r="3" t="72" w="250" /><ent r="3" t="73" w="228" /><ent r="3" t="74" w="209" /><ent r="3" t="75" w="188" /><ent r="3" t="76" w="303" /></phr></stem><stem n="sidebar"><phr n="Sidebar"><ent r="64" t="4" w="76" /><ent r="64" t="4" w="76" /><ent r="92" t="4" w="206" /><ent r="92" t="4" w="206" /></phr><phr n="sidebar"><ent r="3" t="4" w="219" /><ent r="3" t="4" w="219" /><ent r="3" t="4" w="228" /><ent r="3" t="4" w="228" /><ent r="3" t="4" w="244" /><ent r="3" t="4" w="244" /><ent r="3" t="4" w="287" /><ent r="3" t="4" w="287" /><ent r="3" t="4" w="302" /><ent r="3" t="4" w="306" /><ent r="3" t="4" w="306" /><ent r="3" t="7" w="300" /><ent r="3" t="7" w="406" /><ent r="3" t="9" w="68" /><ent r="3" t="11" w="168" /><ent r="3" t="12" w="336" /><ent r="3" t="13" w="78" /><ent r="3" t="16" w="310" /><ent r="3" t="17" w="343" /><ent r="3" t="17" w="485" /><ent r="3" t="17" w="678" /><ent r="3" t="18" w="347" /><ent r="3" t="19" w="330" /><ent r="3" t="20" w="331" /><ent r="3" t="21" w="245" /><ent r="3" t="22" w="334" /><ent r="3" t="23" w="602" /><ent r="3" t="25" w="652" /><ent r="3" t="27" w="488" /><ent r="3" t="29" w="211" /><ent r="3" t="30" w="197" /><ent r="3" t="31" w="192" /><ent r="3" t="32" w="365" /><ent r="3" t="34" w="239" /><ent r="3" t="49" w="81" /><ent r="3" t="50" w="508" /><ent r="3" t="52" w="208" /><ent r="3" t="52" w="308" /><ent r="3" t="52" w="905" /><ent r="3" t="52" w="1020" /><ent r="3" t="53" w="193" /><ent r="3" t="54" w="266" /><ent r="3" t="55" w="278" /><ent r="3" t="56" w="242" /><ent r="3" t="57" w="266" /><ent r="3" t="58" w="116" /></phr></stem><stem n="sid"><phr n="Sidebar"><ent r="64" t="4" w="76" /><ent r="64" t="4" w="76" /><ent r="92" t="4" w="206" /><ent r="92" t="4" w="206" /></phr><phr n="sidebar"><ent r="3" t="4" w="219" /><ent r="3" t="4" w="219" /><ent r="3" t="4" w="228" /><ent r="3" t="4" w="228" /><ent r="3" t="4" w="244" /><ent r="3" t="4" w="244" /><ent r="3" t="4" w="287" /><ent r="3" t="4" w="287" /><ent r="3" t="4" w="302" /><ent r="3" t="4" w="306" /><ent r="3" t="4" w="306" /><ent r="3" t="7" w="300" /><ent r="3" t="7" w="406" /><ent r="3" t="9" w="68" /><ent r="3" t="11" w="168" /><ent r="3" t="12" w="336" /><ent r="3" t="13" w="78" /><ent r="3" t="16" w="310" /><ent r="3" t="17" w="343" /><ent r="3" t="17" w="485" /><ent r="3" t="17" w="678" /><ent r="3" t="18" w="347" /><ent r="3" t="19" w="330" /><ent r="3" t="20" w="331" /><ent r="3" t="21" w="245" /><ent r="3" t="22" w="334" /><ent r="3" t="23" w="602" /><ent r="3" t="25" w="652" /><ent r="3" t="27" w="488" /><ent r="3" t="29" w="211" /><ent r="3" t="30" w="197" /><ent r="3" t="31" w="192" /><ent r="3" t="32" w="365" /><ent r="3" t="34" w="239" /><ent r="3" t="49" w="81" /><ent r="3" t="50" w="508" /><ent r="3" t="52" w="208" /><ent r="3" t="52" w="308" /><ent r="3" t="52" w="905" /><ent r="3" t="52" w="1020" /><ent r="3" t="53" w="193" /><ent r="3" t="54" w="266" /><ent r="3" t="55" w="278" /><ent r="3" t="56" w="242" /><ent r="3" t="57" w="266" /><ent r="3" t="58" w="116" /></phr><phr n="side"><ent r="3" t="4" w="223" /><ent r="3" t="4" w="223" /><ent r="3" t="4" w="343" /><ent r="3" t="4" w="343" /><ent r="3" t="5" w="297" /><ent r="3" t="5" w="297" /><ent r="7" t="10" w="2714" /></phr><phr n="considered"><ent r="3" t="8" w="193" /><ent r="3" t="8" w="193" /><ent r="7" t="15" w="3345" /><ent r="7" t="15" w="3345" /></phr><phr n="front-side"><ent r="7" t="10" w="2713" /><ent r="7" t="10" w="2713" /></phr><phr n="inside"><ent r="7" t="10" w="4687" /><ent r="7" t="10" w="4687" /><ent r="7" t="10" w="4709" /><ent r="7" t="10" w="4709" /><ent r="3" t="44" w="444" /><ent r="3" t="44" w="444" /><ent r="3" t="44" w="1301" /><ent r="3" t="44" w="1301" /><ent r="3" t="45" w="965" /><ent r="3" t="45" w="965" /><ent r="3" t="46" w="602" /><ent r="3" t="46" w="602" /><ent r="3" t="50" w="566" /><ent r="3" t="50" w="566" /></phr><phr n="outside"><ent r="65" t="15" w="3973" /><ent r="65" t="15" w="3973" /><ent r="65" t="23" w="50" /><ent r="65" t="23" w="50" /><ent r="65" t="27" w="60" /><ent r="65" t="27" w="60" /><ent r="3" t="27" w="94" /><ent r="3" t="27" w="94" /><ent r="65" t="28" w="62" /><ent r="65" t="28" w="62" /><ent r="65" t="34" w="298" /><ent r="65" t="34" w="298" /><ent r="65" t="38" w="335" /><ent r="65" t="38" w="335" /><ent r="65" t="43" w="39" /><ent r="65" t="43" w="39" /><ent r="65" t="47" w="238" /><ent r="65" t="47" w="238" /><ent r="69" t="54" w="648" /><ent r="69" t="54" w="648" /><ent r="65" t="55" w="32" /><ent r="65" t="55" w="32" /><ent r="65" t="58" w="253" /><ent r="65" t="58" w="253" /><ent r="3" t="59" w="186" /><ent r="3" t="59" w="186" /></phr><phr n="Inside"><ent r="1000" t="42" w="6" /><ent r="1000" t="42" w="6" /><ent r="102" t="42" w="15" /><ent r="102" t="42" w="15" /><ent r="1000" t="43" w="6" /><ent r="1000" t="43" w="6" /><ent r="102" t="43" w="15" /><ent r="102" t="43" w="15" /><ent r="1000" t="44" w="5" /><ent r="1000" t="44" w="5" /><ent r="102" t="44" w="13" /><ent r="102" t="44" w="13" /><ent r="1000" t="45" w="5" /><ent r="1000" t="45" w="5" /><ent r="102" t="45" w="13" /><ent r="102" t="45" w="13" /><ent r="1000" t="46" w="4" /><ent r="1000" t="46" w="4" /><ent r="102" t="46" w="11" /><ent r="102" t="46" w="11" /></phr></stem><stem n="eba"><phr n="Sidebar"><ent r="64" t="4" w="76" /><ent r="64" t="4" w="76" /><ent r="92" t="4" w="206" /><ent r="92" t="4" w="206" /></phr><phr n="sidebar"><ent r="3" t="4" w="219" /><ent r="3" t="4" w="219" /><ent r="3" t="4" w="228" /><ent r="3" t="4" w="228" /><ent r="3" t="4" w="244" /><ent r="3" t="4" w="244" /><ent r="3" t="4" w="287" /><ent r="3" t="4" w="287" /><ent r="3" t="4" w="302" /><ent r="3" t="4" w="306" /><ent r="3" t="4" w="306" /><ent r="3" t="7" w="300" /><ent r="3" t="7" w="406" /><ent r="3" t="9" w="68" /><ent r="3" t="11" w="168" /><ent r="3" t="12" w="336" /><ent r="3" t="13" w="78" /><ent r="3" t="16" w="310" /><ent r="3" t="17" w="343" /><ent r="3" t="17" w="485" /><ent r="3" t="17" w="678" /><ent r="3" t="18" w="347" /><ent r="3" t="19" w="330" /><ent r="3" t="20" w="331" /><ent r="3" t="21" w="245" /><ent r="3" t="22" w="334" /><ent r="3" t="23" w="602" /><ent r="3" t="25" w="652" /><ent r="3" t="27" w="488" /><ent r="3" t="29" w="211" /><ent r="3" t="30" w="197" /><ent r="3" t="31" w="192" /><ent r="3" t="32" w="365" /><ent r="3" t="34" w="239" /><ent r="3" t="49" w="81" /><ent r="3" t="50" w="508" /><ent r="3" t="52" w="208" /><ent r="3" t="52" w="308" /><ent r="3" t="52" w="905" /><ent r="3" t="52" w="1020" /><ent r="3" t="53" w="193" /><ent r="3" t="54" w="266" /><ent r="3" t="55" w="278" /><ent r="3" t="56" w="242" /><ent r="3" t="57" w="266" /><ent r="3" t="58" w="116" /></phr><phr n="amwebadmin"><ent r="3" t="8" w="266" /></phr><phr n="WEBARCHIVE"><ent r="3" t="50" w="253" /></phr></stem><stem n="deb"><phr n="Sidebar"><ent r="64" t="4" w="76" /><ent r="64" t="4" w="76" /><ent r="92" t="4" w="206" /><ent r="92" t="4" w="206" /></phr><phr n="sidebar"><ent r="3" t="4" w="219" /><ent r="3" t="4" w="219" /><ent r="3" t="4" w="228" /><ent r="3" t="4" w="228" /><ent r="3" t="4" w="244" /><ent r="3" t="4" w="244" /><ent r="3" t="4" w="287" /><ent r="3" t="4" w="287" /><ent r="3" t="4" w="302" /><ent r="3" t="4" w="306" /><ent r="3" t="4" w="306" /><ent r="3" t="7" w="300" /><ent r="3" t="7" w="406" /><ent r="3" t="9" w="68" /><ent r="3" t="11" w="168" /><ent r="3" t="12" w="336" /><ent r="3" t="13" w="78" /><ent r="3" t="16" w="310" /><ent r="3" t="17" w="343" /><ent r="3" t="17" w="485" /><ent r="3" t="17" w="678" /><ent r="3" t="18" w="347" /><ent r="3" t="19" w="330" /><ent r="3" t="20" w="331" /><ent r="3" t="21" w="245" /><ent r="3" t="22" w="334" /><ent r="3" t="23" w="602" /><ent r="3" t="25" w="652" /><ent r="3" t="27" w="488" /><ent r="3" t="29" w="211" /><ent r="3" t="30" w="197" /><ent r="3" t="31" w="192" /><ent r="3" t="32" w="365" /><ent r="3" t="34" w="239" /><ent r="3" t="49" w="81" /><ent r="3" t="50" w="508" /><ent r="3" t="52" w="208" /><ent r="3" t="52" w="308" /><ent r="3" t="52" w="905" /><ent r="3" t="52" w="1020" /><ent r="3" t="53" w="193" /><ent r="3" t="54" w="266" /><ent r="3" t="55" w="278" /><ent r="3" t="56" w="242" /><ent r="3" t="57" w="266" /><ent r="3" t="58" w="116" /></phr></stem><stem n="side"><phr n="Sidebar"><ent r="64" t="4" w="76" /><ent r="64" t="4" w="76" /><ent r="92" t="4" w="206" /><ent r="92" t="4" w="206" /></phr><phr n="sidebar"><ent r="3" t="4" w="219" /><ent r="3" t="4" w="219" /><ent r="3" t="4" w="228" /><ent r="3" t="4" w="228" /><ent r="3" t="4" w="244" /><ent r="3" t="4" w="244" /><ent r="3" t="4" w="287" /><ent r="3" t="4" w="287" /><ent r="3" t="4" w="302" /><ent r="3" t="4" w="306" /><ent r="3" t="4" w="306" /><ent r="3" t="7" w="300" /><ent r="3" t="7" w="406" /><ent r="3" t="9" w="68" /><ent r="3" t="11" w="168" /><ent r="3" t="12" w="336" /><ent r="3" t="13" w="78" /><ent r="3" t="16" w="310" /><ent r="3" t="17" w="343" /><ent r="3" t="17" w="485" /><ent r="3" t="17" w="678" /><ent r="3" t="18" w="347" /><ent r="3" t="19" w="330" /><ent r="3" t="20" w="331" /><ent r="3" t="21" w="245" /><ent r="3" t="22" w="334" /><ent r="3" t="23" w="602" /><ent r="3" t="25" w="652" /><ent r="3" t="27" w="488" /><ent r="3" t="29" w="211" /><ent r="3" t="30" w="197" /><ent r="3" t="31" w="192" /><ent r="3" t="32" w="365" /><ent r="3" t="34" w="239" /><ent r="3" t="49" w="81" /><ent r="3" t="50" w="508" /><ent r="3" t="52" w="208" /><ent r="3" t="52" w="308" /><ent r="3" t="52" w="905" /><ent r="3" t="52" w="1020" /><ent r="3" t="53" w="193" /><ent r="3" t="54" w="266" /><ent r="3" t="55" w="278" /><ent r="3" t="56" w="242" /><ent r="3" t="57" w="266" /><ent r="3" t="58" w="116" /></phr><phr n="side"><ent r="3" t="4" w="223" /><ent r="3" t="4" w="223" /><ent r="3" t="4" w="343" /><ent r="3" t="4" w="343" /><ent r="3" t="5" w="297" /><ent r="3" t="5" w="297" /><ent r="7" t="10" w="2714" /></phr><phr n="considered"><ent r="3" t="8" w="193" /><ent r="3" t="8" w="193" /><ent r="7" t="15" w="3345" /><ent r="7" t="15" w="3345" /></phr><phr n="front-side"><ent r="7" t="10" w="2713" /><ent r="7" t="10" w="2713" /></phr><phr n="inside"><ent r="7" t="10" w="4687" /><ent r="7" t="10" w="4687" /><ent r="7" t="10" w="4709" /><ent r="7" t="10" w="4709" /><ent r="3" t="44" w="444" /><ent r="3" t="44" w="444" /><ent r="3" t="44" w="1301" /><ent r="3" t="44" w="1301" /><ent r="3" t="45" w="965" /><ent r="3" t="45" w="965" /><ent r="3" t="46" w="602" /><ent r="3" t="46" w="602" /><ent r="3" t="50" w="566" /><ent r="3" t="50" w="566" /></phr><phr n="outside"><ent r="65" t="15" w="3973" /><ent r="65" t="15" w="3973" /><ent r="65" t="23" w="50" /><ent r="65" t="23" w="50" /><ent r="65" t="27" w="60" /><ent r="65" t="27" w="60" /><ent r="3" t="27" w="94" /><ent r="3" t="27" w="94" /><ent r="65" t="28" w="62" /><ent r="65" t="28" w="62" /><ent r="65" t="34" w="298" /><ent r="65" t="34" w="298" /><ent r="65" t="38" w="335" /><ent r="65" t="38" w="335" /><ent r="65" t="43" w="39" /><ent r="65" t="43" w="39" /><ent r="65" t="47" w="238" /><ent r="65" t="47" w="238" /><ent r="69" t="54" w="648" /><ent r="69" t="54" w="648" /><ent r="65" t="55" w="32" /><ent r="65" t="55" w="32" /><ent r="65" t="58" w="253" /><ent r="65" t="58" w="253" /><ent r="3" t="59" w="186" /><ent r="3" t="59" w="186" /></phr><phr n="Inside"><ent r="1000" t="42" w="6" /><ent r="1000" t="42" w="6" /><ent r="102" t="42" w="15" /><ent r="102" t="42" w="15" /><ent r="1000" t="43" w="6" /><ent r="1000" t="43" w="6" /><ent r="102" t="43" w="15" /><ent r="102" t="43" w="15" /><ent r="1000" t="44" w="5" /><ent r="1000" t="44" w="5" /><ent r="102" t="44" w="13" /><ent r="102" t="44" w="13" /><ent r="1000" t="45" w="5" /><ent r="1000" t="45" w="5" /><ent r="102" t="45" w="13" /><ent r="102" t="45" w="13" /><ent r="1000" t="46" w="4" /><ent r="1000" t="46" w="4" /><ent r="102" t="46" w="11" /><ent r="102" t="46" w="11" /></phr></stem></index>