<?xml version="1.0" encoding="utf-8"?><index><!-- saved from url=(0016)http://localhost -->
<stem n="veri"><phr n="verified"><ent r="7" t="10" w="5370" /><ent r="7" t="10" w="7069" /><ent r="7" t="10" w="7074" /><ent r="7" t="10" w="7076" /></phr><phr n="Severity"><ent r="7" t="10" w="6406" /><ent r="7" t="10" w="6406" /></phr><phr n="severity"><ent r="7" t="10" w="6413" /><ent r="7" t="10" w="6413" /></phr><phr n="Verification"><ent r="7" t="10" w="7050" /><ent r="7" t="10" w="7050" /><ent r="7" t="71" w="390" /></phr><phr n="recovering"><ent r="3" t="18" w="72" /><ent r="3" t="18" w="72" /></phr><phr n="Verify"><ent r="3" t="40" w="461" /><ent r="3" t="40" w="461" /><ent r="3" t="47" w="766" /><ent r="3" t="47" w="766" /></phr></stem><stem n="erif"><phr n="verified"><ent r="7" t="10" w="5370" /><ent r="7" t="10" w="7069" /><ent r="7" t="10" w="7074" /><ent r="7" t="10" w="7076" /></phr><phr n="Verification"><ent r="7" t="10" w="7050" /><ent r="7" t="10" w="7050" /><ent r="7" t="71" w="390" /></phr><phr n="Verify"><ent r="3" t="40" w="461" /><ent r="3" t="40" w="461" /><ent r="3" t="47" w="766" /><ent r="3" t="47" w="766" /></phr></stem><stem n="rifi"><phr n="verified"><ent r="7" t="10" w="5370" /><ent r="7" t="10" w="7069" /><ent r="7" t="10" w="7074" /><ent r="7" t="10" w="7076" /></phr><phr n="Verification"><ent r="7" t="10" w="7050" /><ent r="7" t="10" w="7050" /><ent r="7" t="71" w="390" /></phr></stem><stem n="verif"><phr n="verified"><ent r="7" t="10" w="5370" /><ent r="7" t="10" w="7069" /><ent r="7" t="10" w="7074" /><ent r="7" t="10" w="7076" /></phr><phr n="Verification"><ent r="7" t="10" w="7050" /><ent r="7" t="10" w="7050" /><ent r="7" t="71" w="390" /></phr><phr n="Verify"><ent r="3" t="40" w="461" /><ent r="3" t="40" w="461" /><ent r="3" t="47" w="766" /><ent r="3" t="47" w="766" /></phr></stem><stem n="erifi"><phr n="verified"><ent r="7" t="10" w="5370" /><ent r="7" t="10" w="7069" /><ent r="7" t="10" w="7074" /><ent r="7" t="10" w="7076" /></phr><phr n="Verification"><ent r="7" t="10" w="7050" /><ent r="7" t="10" w="7050" /><ent r="7" t="71" w="390" /></phr></stem><stem n="rifie"><phr n="verified"><ent r="7" t="10" w="5370" /><ent r="7" t="10" w="7069" /><ent r="7" t="10" w="7074" /><ent r="7" t="10" w="7076" /></phr></stem><stem n="erifie"><phr n="verified"><ent r="7" t="10" w="5370" /><ent r="7" t="10" w="7069" /><ent r="7" t="10" w="7074" /><ent r="7" t="10" w="7076" /></phr></stem><stem n="rified"><phr n="verified"><ent r="7" t="10" w="5370" /><ent r="7" t="10" w="7069" /><ent r="7" t="10" w="7074" /><ent r="7" t="10" w="7076" /></phr></stem><stem n="verifie"><phr n="verified"><ent r="7" t="10" w="5370" /><ent r="7" t="10" w="7069" /><ent r="7" t="10" w="7074" /><ent r="7" t="10" w="7076" /></phr></stem><stem n="erified"><phr n="verified"><ent r="7" t="10" w="5370" /><ent r="7" t="10" w="7069" /><ent r="7" t="10" w="7074" /><ent r="7" t="10" w="7076" /></phr></stem><stem n="verified"><phr n="verified"><ent r="7" t="10" w="5370" /><ent r="7" t="10" w="7069" /><ent r="7" t="10" w="7074" /><ent r="7" t="10" w="7076" /></phr></stem><stem n="unknown"><phr n="unknown"><ent r="7" t="10" w="5388" /><ent r="7" t="10" w="5388" /><ent r="7" t="10" w="7084" /></phr></stem><stem n="unk"><phr n="unknown"><ent r="7" t="10" w="5388" /><ent r="7" t="10" w="5388" /><ent r="7" t="10" w="7084" /></phr></stem><stem n="nkn"><phr n="unknown"><ent r="7" t="10" w="5388" /><ent r="7" t="10" w="5388" /><ent r="7" t="10" w="7084" /></phr></stem><stem n="kno"><phr n="unknown"><ent r="7" t="10" w="5388" /><ent r="7" t="10" w="5388" /><ent r="7" t="10" w="7084" /></phr><phr n="known"><ent r="7" t="15" w="1703" /><ent r="7" t="15" w="1703" /></phr></stem><stem n="unkn"><phr n="unknown"><ent r="7" t="10" w="5388" /><ent r="7" t="10" w="5388" /><ent r="7" t="10" w="7084" /></phr></stem><stem n="nkno"><phr n="unknown"><ent r="7" t="10" w="5388" /><ent r="7" t="10" w="5388" /><ent r="7" t="10" w="7084" /></phr></stem><stem n="know"><phr n="unknown"><ent r="7" t="10" w="5388" /><ent r="7" t="10" w="5388" /><ent r="7" t="10" w="7084" /></phr><phr n="known"><ent r="7" t="15" w="1703" /><ent r="7" t="15" w="1703" /></phr></stem><stem n="nown"><phr n="unknown"><ent r="7" t="10" w="5388" /><ent r="7" t="10" w="5388" /><ent r="7" t="10" w="7084" /></phr><phr n="known"><ent r="7" t="15" w="1703" /><ent r="7" t="15" w="1703" /></phr></stem><stem n="unkno"><phr n="unknown"><ent r="7" t="10" w="5388" /><ent r="7" t="10" w="5388" /><ent r="7" t="10" w="7084" /></phr></stem><stem n="nknow"><phr n="unknown"><ent r="7" t="10" w="5388" /><ent r="7" t="10" w="5388" /><ent r="7" t="10" w="7084" /></phr></stem><stem n="known"><phr n="unknown"><ent r="7" t="10" w="5388" /><ent r="7" t="10" w="5388" /><ent r="7" t="10" w="7084" /></phr><phr n="known"><ent r="7" t="15" w="1703" /><ent r="7" t="15" w="1703" /></phr></stem><stem n="unknow"><phr n="unknown"><ent r="7" t="10" w="5388" /><ent r="7" t="10" w="5388" /><ent r="7" t="10" w="7084" /></phr></stem><stem n="nknown"><phr n="unknown"><ent r="7" t="10" w="5388" /><ent r="7" t="10" w="5388" /><ent r="7" t="10" w="7084" /></phr></stem><stem n="valid"><phr n="valid"><ent r="7" t="10" w="5394" /><ent r="7" t="10" w="5394" /><ent r="3" t="33" w="232" /><ent r="3" t="33" w="232" /><ent r="3" t="33" w="273" /><ent r="3" t="33" w="273" /><ent r="7" t="54" w="680" /><ent r="7" t="54" w="680" /><ent r="7" t="58" w="301" /><ent r="7" t="58" w="301" /><ent r="3" t="81" w="315" /><ent r="3" t="81" w="315" /><ent r="3" t="81" w="356" /><ent r="3" t="81" w="356" /></phr></stem><stem n="lid"><phr n="valid"><ent r="7" t="10" w="5394" /><ent r="7" t="10" w="5394" /><ent r="3" t="33" w="232" /><ent r="3" t="33" w="232" /><ent r="3" t="33" w="273" /><ent r="3" t="33" w="273" /><ent r="7" t="54" w="680" /><ent r="7" t="54" w="680" /><ent r="7" t="58" w="301" /><ent r="7" t="58" w="301" /><ent r="3" t="81" w="315" /><ent r="3" t="81" w="315" /><ent r="3" t="81" w="356" /><ent r="3" t="81" w="356" /></phr></stem><stem n="vali"><phr n="valid"><ent r="7" t="10" w="5394" /><ent r="7" t="10" w="5394" /><ent r="3" t="33" w="232" /><ent r="3" t="33" w="232" /><ent r="3" t="33" w="273" /><ent r="3" t="33" w="273" /><ent r="7" t="54" w="680" /><ent r="7" t="54" w="680" /><ent r="7" t="58" w="301" /><ent r="7" t="58" w="301" /><ent r="3" t="81" w="315" /><ent r="3" t="81" w="315" /><ent r="3" t="81" w="356" /><ent r="3" t="81" w="356" /></phr></stem><stem n="alid"><phr n="valid"><ent r="7" t="10" w="5394" /><ent r="7" t="10" w="5394" /><ent r="3" t="33" w="232" /><ent r="3" t="33" w="232" /><ent r="3" t="33" w="273" /><ent r="3" t="33" w="273" /><ent r="7" t="54" w="680" /><ent r="7" t="54" w="680" /><ent r="7" t="58" w="301" /><ent r="7" t="58" w="301" /><ent r="3" t="81" w="315" /><ent r="3" t="81" w="315" /><ent r="3" t="81" w="356" /><ent r="3" t="81" w="356" /></phr></stem><stem n="meantim"><phr n="meantime"><ent r="7" t="10" w="5407" /></phr></stem><stem n="eant"><phr n="meantime"><ent r="7" t="10" w="5407" /></phr></stem><stem n="anti"><phr n="meantime"><ent r="7" t="10" w="5407" /></phr></stem><stem n="ntim"><phr n="meantime"><ent r="7" t="10" w="5407" /></phr></stem><stem n="meant"><phr n="meantime"><ent r="7" t="10" w="5407" /></phr></stem><stem n="eanti"><phr n="meantime"><ent r="7" t="10" w="5407" /></phr></stem><stem n="antim"><phr n="meantime"><ent r="7" t="10" w="5407" /></phr></stem><stem n="ntime"><phr n="meantime"><ent r="7" t="10" w="5407" /></phr></stem><stem n="meanti"><phr n="meantime"><ent r="7" t="10" w="5407" /></phr></stem><stem n="eantim"><phr n="meantime"><ent r="7" t="10" w="5407" /></phr></stem><stem n="antime"><phr n="meantime"><ent r="7" t="10" w="5407" /></phr></stem><stem n="eantime"><phr n="meantime"><ent r="7" t="10" w="5407" /></phr></stem><stem n="meantime"><phr n="meantime"><ent r="7" t="10" w="5407" /></phr></stem><stem n="apart"><phr n="apart"><ent r="7" t="10" w="5443" /><ent r="7" t="10" w="5443" /></phr></stem><stem n="apa"><phr n="apart"><ent r="7" t="10" w="5443" /><ent r="7" t="10" w="5443" /></phr><phr n="capacity"><ent r="7" t="10" w="5663" /><ent r="7" t="10" w="5663" /><ent r="7" t="10" w="5738" /><ent r="7" t="10" w="5738" /><ent r="7" t="10" w="5754" /><ent r="7" t="10" w="5754" /><ent r="7" t="10" w="5765" /><ent r="7" t="10" w="5765" /><ent r="7" t="15" w="1303" /><ent r="7" t="15" w="1303" /><ent r="7" t="15" w="1315" /><ent r="7" t="15" w="1315" /><ent r="7" t="15" w="1324" /><ent r="7" t="15" w="1371" /><ent r="7" t="15" w="1371" /><ent r="7" t="15" w="1383" /><ent r="7" t="15" w="1383" /></phr><phr n="Capacity"><ent r="7" t="15" w="1295" /><ent r="7" t="15" w="1295" /><ent r="7" t="15" w="1410" /><ent r="7" t="15" w="1410" /><ent r="7" t="15" w="1426" /><ent r="7" t="15" w="1426" /></phr><phr n="Capable"><ent r="7" t="15" w="1665" /><ent r="7" t="15" w="1665" /></phr><phr n="capable"><ent r="7" t="15" w="1689" /><ent r="7" t="15" w="1689" /></phr><phr n="capabilities"><ent r="70" t="15" w="2712" /><ent r="70" t="15" w="2712" /></phr></stem><stem n="apar"><phr n="apart"><ent r="7" t="10" w="5443" /><ent r="7" t="10" w="5443" /></phr></stem><stem n="wake"><phr n="Wake"><ent r="7" t="10" w="5450" /><ent r="7" t="10" w="5450" /><ent r="7" t="10" w="5462" /><ent r="7" t="10" w="5483" /><ent r="7" t="10" w="5483" /><ent r="7" t="10" w="5498" /></phr><phr n="Wake-on-LAN"><ent r="7" t="10" w="5462" /><ent r="7" t="10" w="5462" /><ent r="7" t="10" w="5498" /><ent r="7" t="10" w="5498" /></phr><phr n="Wake-on"><ent r="7" t="10" w="5462" /><ent r="7" t="10" w="5498" /></phr><phr n="awakening"><ent r="7" t="10" w="5468" /><ent r="7" t="10" w="5468" /></phr></stem><stem n="wak"><phr n="Wake"><ent r="7" t="10" w="5450" /><ent r="7" t="10" w="5450" /><ent r="7" t="10" w="5462" /><ent r="7" t="10" w="5483" /><ent r="7" t="10" w="5483" /><ent r="7" t="10" w="5498" /></phr><phr n="Wake-on-LAN"><ent r="7" t="10" w="5462" /><ent r="7" t="10" w="5462" /><ent r="7" t="10" w="5498" /><ent r="7" t="10" w="5498" /></phr><phr n="Wake-on"><ent r="7" t="10" w="5462" /><ent r="7" t="10" w="5498" /></phr><phr n="awakening"><ent r="7" t="10" w="5468" /><ent r="7" t="10" w="5468" /></phr></stem><stem n="wake-on-lan"><phr n="Wake-on-LAN"><ent r="7" t="10" w="5462" /><ent r="7" t="10" w="5462" /><ent r="7" t="10" w="5498" /><ent r="7" t="10" w="5498" /></phr></stem><stem n="e-o"><phr n="Wake-on-LAN"><ent r="7" t="10" w="5462" /><ent r="7" t="10" w="5462" /><ent r="7" t="10" w="5498" /><ent r="7" t="10" w="5498" /></phr><phr n="Wake-on"><ent r="7" t="10" w="5462" /><ent r="7" t="10" w="5498" /></phr></stem><stem n="n-l"><phr n="Wake-on-LAN"><ent r="7" t="10" w="5462" /><ent r="7" t="10" w="5462" /><ent r="7" t="10" w="5498" /><ent r="7" t="10" w="5498" /></phr><phr n="on-LAN"><ent r="7" t="10" w="5463" /><ent r="7" t="10" w="5499" /></phr></stem><stem n="ke-"><phr n="Wake-on-LAN"><ent r="7" t="10" w="5462" /><ent r="7" t="10" w="5462" /><ent r="7" t="10" w="5498" /><ent r="7" t="10" w="5498" /></phr><phr n="Wake-on"><ent r="7" t="10" w="5462" /><ent r="7" t="10" w="5498" /></phr></stem><stem n="-on-"><phr n="Wake-on-LAN"><ent r="7" t="10" w="5462" /><ent r="7" t="10" w="5462" /><ent r="7" t="10" w="5498" /><ent r="7" t="10" w="5498" /></phr></stem><stem n="ake-"><phr n="Wake-on-LAN"><ent r="7" t="10" w="5462" /><ent r="7" t="10" w="5462" /><ent r="7" t="10" w="5498" /><ent r="7" t="10" w="5498" /></phr><phr n="Wake-on"><ent r="7" t="10" w="5462" /><ent r="7" t="10" w="5498" /></phr></stem><stem n="on-l"><phr n="Wake-on-LAN"><ent r="7" t="10" w="5462" /><ent r="7" t="10" w="5462" /><ent r="7" t="10" w="5498" /><ent r="7" t="10" w="5498" /></phr><phr n="on-LAN"><ent r="7" t="10" w="5463" /><ent r="7" t="10" w="5499" /></phr></stem><stem n="ke-o"><phr n="Wake-on-LAN"><ent r="7" t="10" w="5462" /><ent r="7" t="10" w="5462" /><ent r="7" t="10" w="5498" /><ent r="7" t="10" w="5498" /></phr><phr n="Wake-on"><ent r="7" t="10" w="5462" /><ent r="7" t="10" w="5498" /></phr></stem><stem n="n-la"><phr n="Wake-on-LAN"><ent r="7" t="10" w="5462" /><ent r="7" t="10" w="5462" /><ent r="7" t="10" w="5498" /><ent r="7" t="10" w="5498" /></phr><phr n="on-LAN"><ent r="7" t="10" w="5463" /><ent r="7" t="10" w="5499" /></phr></stem><stem n="e-on"><phr n="Wake-on-LAN"><ent r="7" t="10" w="5462" /><ent r="7" t="10" w="5462" /><ent r="7" t="10" w="5498" /><ent r="7" t="10" w="5498" /></phr><phr n="Wake-on"><ent r="7" t="10" w="5462" /><ent r="7" t="10" w="5498" /></phr></stem><stem n="wake-"><phr n="Wake-on-LAN"><ent r="7" t="10" w="5462" /><ent r="7" t="10" w="5462" /><ent r="7" t="10" w="5498" /><ent r="7" t="10" w="5498" /></phr><phr n="Wake-on"><ent r="7" t="10" w="5462" /><ent r="7" t="10" w="5498" /></phr></stem><stem n="on-la"><phr n="Wake-on-LAN"><ent r="7" t="10" w="5462" /><ent r="7" t="10" w="5462" /><ent r="7" t="10" w="5498" /><ent r="7" t="10" w="5498" /></phr><phr n="on-LAN"><ent r="7" t="10" w="5463" /><ent r="7" t="10" w="5499" /></phr></stem><stem n="ake-o"><phr n="Wake-on-LAN"><ent r="7" t="10" w="5462" /><ent r="7" t="10" w="5462" /><ent r="7" t="10" w="5498" /><ent r="7" t="10" w="5498" /></phr><phr n="Wake-on"><ent r="7" t="10" w="5462" /><ent r="7" t="10" w="5498" /></phr></stem><stem n="n-lan"><phr n="Wake-on-LAN"><ent r="7" t="10" w="5462" /><ent r="7" t="10" w="5462" /><ent r="7" t="10" w="5498" /><ent r="7" t="10" w="5498" /></phr><phr n="on-LAN"><ent r="7" t="10" w="5463" /><ent r="7" t="10" w="5499" /></phr></stem><stem n="ke-on"><phr n="Wake-on-LAN"><ent r="7" t="10" w="5462" /><ent r="7" t="10" w="5462" /><ent r="7" t="10" w="5498" /><ent r="7" t="10" w="5498" /></phr><phr n="Wake-on"><ent r="7" t="10" w="5462" /><ent r="7" t="10" w="5498" /></phr></stem><stem n="e-on-"><phr n="Wake-on-LAN"><ent r="7" t="10" w="5462" /><ent r="7" t="10" w="5462" /><ent r="7" t="10" w="5498" /><ent r="7" t="10" w="5498" /></phr></stem><stem n="-on-l"><phr n="Wake-on-LAN"><ent r="7" t="10" w="5462" /><ent r="7" t="10" w="5462" /><ent r="7" t="10" w="5498" /><ent r="7" t="10" w="5498" /></phr></stem><stem n="wake-o"><phr n="Wake-on-LAN"><ent r="7" t="10" w="5462" /><ent r="7" t="10" w="5462" /><ent r="7" t="10" w="5498" /><ent r="7" t="10" w="5498" /></phr><phr n="Wake-on"><ent r="7" t="10" w="5462" /><ent r="7" t="10" w="5498" /></phr></stem><stem n="ake-on"><phr n="Wake-on-LAN"><ent r="7" t="10" w="5462" /><ent r="7" t="10" w="5462" /><ent r="7" t="10" w="5498" /><ent r="7" t="10" w="5498" /></phr><phr n="Wake-on"><ent r="7" t="10" w="5462" /><ent r="7" t="10" w="5498" /></phr></stem><stem n="ke-on-"><phr n="Wake-on-LAN"><ent r="7" t="10" w="5462" /><ent r="7" t="10" w="5462" /><ent r="7" t="10" w="5498" /><ent r="7" t="10" w="5498" /></phr></stem><stem n="e-on-l"><phr n="Wake-on-LAN"><ent r="7" t="10" w="5462" /><ent r="7" t="10" w="5462" /><ent r="7" t="10" w="5498" /><ent r="7" t="10" w="5498" /></phr></stem><stem n="-on-la"><phr n="Wake-on-LAN"><ent r="7" t="10" w="5462" /><ent r="7" t="10" w="5462" /><ent r="7" t="10" w="5498" /><ent r="7" t="10" w="5498" /></phr></stem><stem n="on-lan"><phr n="Wake-on-LAN"><ent r="7" t="10" w="5462" /><ent r="7" t="10" w="5462" /><ent r="7" t="10" w="5498" /><ent r="7" t="10" w="5498" /></phr><phr n="on-LAN"><ent r="7" t="10" w="5463" /><ent r="7" t="10" w="5499" /></phr></stem><stem n="wake-on"><phr n="Wake-on-LAN"><ent r="7" t="10" w="5462" /><ent r="7" t="10" w="5462" /><ent r="7" t="10" w="5498" /><ent r="7" t="10" w="5498" /></phr><phr n="Wake-on"><ent r="7" t="10" w="5462" /><ent r="7" t="10" w="5498" /></phr></stem><stem n="ake-on-"><phr n="Wake-on-LAN"><ent r="7" t="10" w="5462" /><ent r="7" t="10" w="5462" /><ent r="7" t="10" w="5498" /><ent r="7" t="10" w="5498" /></phr></stem><stem n="ke-on-l"><phr n="Wake-on-LAN"><ent r="7" t="10" w="5462" /><ent r="7" t="10" w="5462" /><ent r="7" t="10" w="5498" /><ent r="7" t="10" w="5498" /></phr></stem><stem n="e-on-la"><phr n="Wake-on-LAN"><ent r="7" t="10" w="5462" /><ent r="7" t="10" w="5462" /><ent r="7" t="10" w="5498" /><ent r="7" t="10" w="5498" /></phr></stem><stem n="-on-lan"><phr n="Wake-on-LAN"><ent r="7" t="10" w="5462" /><ent r="7" t="10" w="5462" /><ent r="7" t="10" w="5498" /><ent r="7" t="10" w="5498" /></phr></stem><stem n="wake-on-"><phr n="Wake-on-LAN"><ent r="7" t="10" w="5462" /><ent r="7" t="10" w="5462" /><ent r="7" t="10" w="5498" /><ent r="7" t="10" w="5498" /></phr></stem><stem n="ake-on-l"><phr n="Wake-on-LAN"><ent r="7" t="10" w="5462" /><ent r="7" t="10" w="5462" /><ent r="7" t="10" w="5498" /><ent r="7" t="10" w="5498" /></phr></stem><stem n="ke-on-la"><phr n="Wake-on-LAN"><ent r="7" t="10" w="5462" /><ent r="7" t="10" w="5462" /><ent r="7" t="10" w="5498" /><ent r="7" t="10" w="5498" /></phr></stem><stem n="e-on-lan"><phr n="Wake-on-LAN"><ent r="7" t="10" w="5462" /><ent r="7" t="10" w="5462" /><ent r="7" t="10" w="5498" /><ent r="7" t="10" w="5498" /></phr></stem><stem n="wake-on-l"><phr n="Wake-on-LAN"><ent r="7" t="10" w="5462" /><ent r="7" t="10" w="5462" /><ent r="7" t="10" w="5498" /><ent r="7" t="10" w="5498" /></phr></stem><stem n="ake-on-la"><phr n="Wake-on-LAN"><ent r="7" t="10" w="5462" /><ent r="7" t="10" w="5462" /><ent r="7" t="10" w="5498" /><ent r="7" t="10" w="5498" /></phr></stem><stem n="ke-on-lan"><phr n="Wake-on-LAN"><ent r="7" t="10" w="5462" /><ent r="7" t="10" w="5462" /><ent r="7" t="10" w="5498" /><ent r="7" t="10" w="5498" /></phr></stem><stem n="wake-on-la"><phr n="Wake-on-LAN"><ent r="7" t="10" w="5462" /><ent r="7" t="10" w="5462" /><ent r="7" t="10" w="5498" /><ent r="7" t="10" w="5498" /></phr></stem><stem n="ake-on-lan"><phr n="Wake-on-LAN"><ent r="7" t="10" w="5462" /><ent r="7" t="10" w="5462" /><ent r="7" t="10" w="5498" /><ent r="7" t="10" w="5498" /></phr></stem><stem n="urni"><phr n="turning"><ent r="7" t="10" w="5465" /><ent r="7" t="10" w="5465" /></phr></stem><stem n="turni"><phr n="turning"><ent r="7" t="10" w="5465" /><ent r="7" t="10" w="5465" /></phr></stem><stem n="urnin"><phr n="turning"><ent r="7" t="10" w="5465" /><ent r="7" t="10" w="5465" /></phr></stem><stem n="turnin"><phr n="turning"><ent r="7" t="10" w="5465" /><ent r="7" t="10" w="5465" /></phr></stem><stem n="urning"><phr n="turning"><ent r="7" t="10" w="5465" /><ent r="7" t="10" w="5465" /></phr></stem><stem n="turning"><phr n="turning"><ent r="7" t="10" w="5465" /><ent r="7" t="10" w="5465" /></phr></stem><stem n="awaken"><phr n="awakening"><ent r="7" t="10" w="5468" /><ent r="7" t="10" w="5468" /></phr></stem><stem n="awa"><phr n="awakening"><ent r="7" t="10" w="5468" /><ent r="7" t="10" w="5468" /></phr></stem><stem n="awak"><phr n="awakening"><ent r="7" t="10" w="5468" /><ent r="7" t="10" w="5468" /></phr></stem><stem n="keni"><phr n="awakening"><ent r="7" t="10" w="5468" /><ent r="7" t="10" w="5468" /></phr></stem><stem n="awake"><phr n="awakening"><ent r="7" t="10" w="5468" /><ent r="7" t="10" w="5468" /></phr></stem><stem n="waken"><phr n="awakening"><ent r="7" t="10" w="5468" /><ent r="7" t="10" w="5468" /></phr></stem><stem n="akeni"><phr n="awakening"><ent r="7" t="10" w="5468" /><ent r="7" t="10" w="5468" /></phr></stem><stem n="kenin"><phr n="awakening"><ent r="7" t="10" w="5468" /><ent r="7" t="10" w="5468" /></phr></stem><stem n="wakeni"><phr n="awakening"><ent r="7" t="10" w="5468" /><ent r="7" t="10" w="5468" /></phr></stem><stem n="akenin"><phr n="awakening"><ent r="7" t="10" w="5468" /><ent r="7" t="10" w="5468" /></phr></stem><stem n="kening"><phr n="awakening"><ent r="7" t="10" w="5468" /><ent r="7" t="10" w="5468" /></phr></stem><stem n="awakeni"><phr n="awakening"><ent r="7" t="10" w="5468" /><ent r="7" t="10" w="5468" /></phr></stem><stem n="wakenin"><phr n="awakening"><ent r="7" t="10" w="5468" /><ent r="7" t="10" w="5468" /></phr></stem><stem n="akening"><phr n="awakening"><ent r="7" t="10" w="5468" /><ent r="7" t="10" w="5468" /></phr></stem><stem n="awakenin"><phr n="awakening"><ent r="7" t="10" w="5468" /><ent r="7" t="10" w="5468" /></phr></stem><stem n="wakening"><phr n="awakening"><ent r="7" t="10" w="5468" /><ent r="7" t="10" w="5468" /></phr></stem><stem n="awakening"><phr n="awakening"><ent r="7" t="10" w="5468" /><ent r="7" t="10" w="5468" /></phr></stem><stem n="sleep"><phr n="sleep"><ent r="7" t="10" w="5472" /><ent r="7" t="10" w="5472" /></phr></stem><stem n="sle"><phr n="sleep"><ent r="7" t="10" w="5472" /><ent r="7" t="10" w="5472" /></phr></stem><stem n="lee"><phr n="sleep"><ent r="7" t="10" w="5472" /><ent r="7" t="10" w="5472" /></phr></stem><stem n="eep"><phr n="sleep"><ent r="7" t="10" w="5472" /><ent r="7" t="10" w="5472" /></phr></stem><stem n="slee"><phr n="sleep"><ent r="7" t="10" w="5472" /><ent r="7" t="10" w="5472" /></phr></stem><stem n="leep"><phr n="sleep"><ent r="7" t="10" w="5472" /><ent r="7" t="10" w="5472" /></phr></stem><stem n="startup"><phr n="Startup"><ent r="7" t="10" w="5502" /><ent r="7" t="10" w="5502" /><ent r="7" t="10" w="5525" /><ent r="7" t="10" w="5525" /></phr><phr n="startup"><ent r="3" t="12" w="178" /><ent r="3" t="12" w="178" /><ent r="4" t="12" w="432" /><ent r="4" t="12" w="432" /><ent r="3" t="12" w="451" /><ent r="3" t="12" w="451" /></phr></stem><stem n="tup"><phr n="Startup"><ent r="7" t="10" w="5502" /><ent r="7" t="10" w="5502" /><ent r="7" t="10" w="5525" /><ent r="7" t="10" w="5525" /></phr><phr n="startup"><ent r="3" t="12" w="178" /><ent r="3" t="12" w="178" /><ent r="4" t="12" w="432" /><ent r="4" t="12" w="432" /><ent r="3" t="12" w="451" /><ent r="3" t="12" w="451" /></phr></stem><stem n="artu"><phr n="Startup"><ent r="7" t="10" w="5502" /><ent r="7" t="10" w="5502" /><ent r="7" t="10" w="5525" /><ent r="7" t="10" w="5525" /></phr><phr n="startup"><ent r="3" t="12" w="178" /><ent r="3" t="12" w="178" /><ent r="4" t="12" w="432" /><ent r="4" t="12" w="432" /><ent r="3" t="12" w="451" /><ent r="3" t="12" w="451" /></phr></stem><stem n="rtup"><phr n="Startup"><ent r="7" t="10" w="5502" /><ent r="7" t="10" w="5502" /><ent r="7" t="10" w="5525" /><ent r="7" t="10" w="5525" /></phr><phr n="startup"><ent r="3" t="12" w="178" /><ent r="3" t="12" w="178" /><ent r="4" t="12" w="432" /><ent r="4" t="12" w="432" /><ent r="3" t="12" w="451" /><ent r="3" t="12" w="451" /></phr></stem><stem n="tartu"><phr n="Startup"><ent r="7" t="10" w="5502" /><ent r="7" t="10" w="5502" /><ent r="7" t="10" w="5525" /><ent r="7" t="10" w="5525" /></phr><phr n="startup"><ent r="3" t="12" w="178" /><ent r="3" t="12" w="178" /><ent r="4" t="12" w="432" /><ent r="4" t="12" w="432" /><ent r="3" t="12" w="451" /><ent r="3" t="12" w="451" /></phr></stem><stem n="artup"><phr n="Startup"><ent r="7" t="10" w="5502" /><ent r="7" t="10" w="5502" /><ent r="7" t="10" w="5525" /><ent r="7" t="10" w="5525" /></phr><phr n="startup"><ent r="3" t="12" w="178" /><ent r="3" t="12" w="178" /><ent r="4" t="12" w="432" /><ent r="4" t="12" w="432" /><ent r="3" t="12" w="451" /><ent r="3" t="12" w="451" /></phr></stem><stem n="startu"><phr n="Startup"><ent r="7" t="10" w="5502" /><ent r="7" t="10" w="5502" /><ent r="7" t="10" w="5525" /><ent r="7" t="10" w="5525" /></phr><phr n="startup"><ent r="3" t="12" w="178" /><ent r="3" t="12" w="178" /><ent r="4" t="12" w="432" /><ent r="4" t="12" w="432" /><ent r="3" t="12" w="451" /><ent r="3" t="12" w="451" /></phr></stem><stem n="tartup"><phr n="Startup"><ent r="7" t="10" w="5502" /><ent r="7" t="10" w="5502" /><ent r="7" t="10" w="5525" /><ent r="7" t="10" w="5525" /></phr><phr n="startup"><ent r="3" t="12" w="178" /><ent r="3" t="12" w="178" /><ent r="4" t="12" w="432" /><ent r="4" t="12" w="432" /><ent r="3" t="12" w="451" /><ent r="3" t="12" w="451" /></phr></stem><stem n="start-up"><phr n="start-up"><ent r="7" t="10" w="5514" /><ent r="7" t="10" w="5514" /><ent r="7" t="10" w="5537" /><ent r="7" t="10" w="5537" /></phr></stem><stem n="rt-"><phr n="start-up"><ent r="7" t="10" w="5514" /><ent r="7" t="10" w="5514" /><ent r="7" t="10" w="5537" /><ent r="7" t="10" w="5537" /></phr></stem><stem n="t-u"><phr n="start-up"><ent r="7" t="10" w="5514" /><ent r="7" t="10" w="5514" /><ent r="7" t="10" w="5537" /><ent r="7" t="10" w="5537" /></phr></stem><stem n="-up"><phr n="start-up"><ent r="7" t="10" w="5514" /><ent r="7" t="10" w="5514" /><ent r="7" t="10" w="5537" /><ent r="7" t="10" w="5537" /></phr></stem><stem n="t-up"><phr n="start-up"><ent r="7" t="10" w="5514" /><ent r="7" t="10" w="5514" /><ent r="7" t="10" w="5537" /><ent r="7" t="10" w="5537" /></phr></stem><stem n="art-"><phr n="start-up"><ent r="7" t="10" w="5514" /><ent r="7" t="10" w="5514" /><ent r="7" t="10" w="5537" /><ent r="7" t="10" w="5537" /></phr></stem><stem n="rt-u"><phr n="start-up"><ent r="7" t="10" w="5514" /><ent r="7" t="10" w="5514" /><ent r="7" t="10" w="5537" /><ent r="7" t="10" w="5537" /></phr></stem><stem n="tart-"><phr n="start-up"><ent r="7" t="10" w="5514" /><ent r="7" t="10" w="5514" /><ent r="7" t="10" w="5537" /><ent r="7" t="10" w="5537" /></phr></stem><stem n="art-u"><phr n="start-up"><ent r="7" t="10" w="5514" /><ent r="7" t="10" w="5514" /><ent r="7" t="10" w="5537" /><ent r="7" t="10" w="5537" /></phr></stem><stem n="rt-up"><phr n="start-up"><ent r="7" t="10" w="5514" /><ent r="7" t="10" w="5514" /><ent r="7" t="10" w="5537" /><ent r="7" t="10" w="5537" /></phr></stem><stem n="start-"><phr n="start-up"><ent r="7" t="10" w="5514" /><ent r="7" t="10" w="5514" /><ent r="7" t="10" w="5537" /><ent r="7" t="10" w="5537" /></phr></stem><stem n="tart-u"><phr n="start-up"><ent r="7" t="10" w="5514" /><ent r="7" t="10" w="5514" /><ent r="7" t="10" w="5537" /><ent r="7" t="10" w="5537" /></phr></stem><stem n="art-up"><phr n="start-up"><ent r="7" t="10" w="5514" /><ent r="7" t="10" w="5514" /><ent r="7" t="10" w="5537" /><ent r="7" t="10" w="5537" /></phr></stem><stem n="start-u"><phr n="start-up"><ent r="7" t="10" w="5514" /><ent r="7" t="10" w="5514" /><ent r="7" t="10" w="5537" /><ent r="7" t="10" w="5537" /></phr></stem><stem n="tart-up"><phr n="start-up"><ent r="7" t="10" w="5514" /><ent r="7" t="10" w="5514" /><ent r="7" t="10" w="5537" /><ent r="7" t="10" w="5537" /></phr></stem><stem n="label"><phr n="label"><ent r="7" t="10" w="5569" /><ent r="7" t="10" w="5569" /><ent r="7" t="10" w="5987" /><ent r="7" t="10" w="5987" /><ent r="69" t="15" w="1825" /><ent r="69" t="15" w="1825" /><ent r="65" t="33" w="315" /><ent r="65" t="33" w="315" /><ent r="65" t="81" w="398" /><ent r="65" t="81" w="398" /></phr></stem><stem n="abe"><phr n="label"><ent r="7" t="10" w="5569" /><ent r="7" t="10" w="5569" /><ent r="7" t="10" w="5987" /><ent r="7" t="10" w="5987" /><ent r="69" t="15" w="1825" /><ent r="69" t="15" w="1825" /><ent r="65" t="33" w="315" /><ent r="65" t="33" w="315" /><ent r="65" t="81" w="398" /><ent r="65" t="81" w="398" /></phr></stem><stem n="labe"><phr n="label"><ent r="7" t="10" w="5569" /><ent r="7" t="10" w="5569" /><ent r="7" t="10" w="5987" /><ent r="7" t="10" w="5987" /><ent r="69" t="15" w="1825" /><ent r="69" t="15" w="1825" /><ent r="65" t="33" w="315" /><ent r="65" t="33" w="315" /><ent r="65" t="81" w="398" /><ent r="65" t="81" w="398" /></phr></stem><stem n="abel"><phr n="label"><ent r="7" t="10" w="5569" /><ent r="7" t="10" w="5569" /><ent r="7" t="10" w="5987" /><ent r="7" t="10" w="5987" /><ent r="69" t="15" w="1825" /><ent r="69" t="15" w="1825" /><ent r="65" t="33" w="315" /><ent r="65" t="33" w="315" /><ent r="65" t="81" w="398" /><ent r="65" t="81" w="398" /></phr></stem></index>